{
  "alert": {
    "id": "f383471b-f90f-4527-8689-5b8d113bbe01",
    "policy": {
      "id": "45babb2e-c53d-4297-a729-b224124ae4a5",
      "name": "vuln_test",
      "categories": [
        "Vulnerability Management"
      ],
      "lifecycleStages": [
        "BUILD",
        "DEPLOY"
      ],
      "severity": "LOW_SEVERITY",
      "notifiers": [
        "1f2c61e3-c9bf-4458-8af4-b2e844c70510"
      ],
      "lastUpdated": "2023-03-18T15:35:16.446828465Z",
      "SORTName": "vuln_test",
      "SORTLifecycleStage": "BUILD,DEPLOY",
      "policyVersion": "1.1",
      "policySections": [
        {
          "sectionName": "Policy Section 1",
          "policyGroups": [
            {
              "fieldName": "CVSS",
              "values": [
                {
                  "value": ">5"
                }
              ]
            }
          ]
        }
      ]
    },
    "clusterId": "1baaa6fd-bf18-4d39-89b9-58ab240b5944",
    "clusterName": "local-cluster",
    "namespace": "openshift-kube-scheduler",
    "namespaceId": "09811b6e-79af-4607-a302-1106761a4d8f",
    "deployment": {
      "id": "8d09492a-7107-46f4-b162-9044e740722d",
      "name": "openshift-kube-scheduler-master0",
      "type": "Pod",
      "namespace": "openshift-kube-scheduler",
      "namespaceId": "09811b6e-79af-4607-a302-1106761a4d8f",
      "labels": {
        "app": "openshift-kube-scheduler",
        "revision": "7",
        "scheduler": "true"
      },
      "clusterId": "1baaa6fd-bf18-4d39-89b9-58ab240b5944",
      "clusterName": "local-cluster",
      "containers": [
        {
          "image": {
            "id": "sha256:662c00a50b8327cc39963577d3e11aa71458b3888ce06223a4501679a28fecd1",
            "name": {
              "registry": "quay.io",
              "remote": "openshift-release-dev/ocp-v4.0-art-dev",
              "fullName": "quay.io/openshift-release-dev/ocp-v4.0-art-dev@sha256:662c00a50b8327cc39963577d3e11aa71458b3888ce06223a4501679a28fecd1"
            }
          },
          "name": "kube-scheduler"
        },
        {
          "image": {
            "id": "sha256:e045fad043f28570b754619999ffb356bedee81ff842c56a32b1b13588fc1651",
            "name": {
              "registry": "quay.io",
              "remote": "openshift-release-dev/ocp-v4.0-art-dev",
              "fullName": "quay.io/openshift-release-dev/ocp-v4.0-art-dev@sha256:e045fad043f28570b754619999ffb356bedee81ff842c56a32b1b13588fc1651"
            }
          },
          "name": "kube-scheduler-cert-syncer"
        },
        {
          "image": {
            "id": "sha256:e045fad043f28570b754619999ffb356bedee81ff842c56a32b1b13588fc1651",
            "name": {
              "registry": "quay.io",
              "remote": "openshift-release-dev/ocp-v4.0-art-dev",
              "fullName": "quay.io/openshift-release-dev/ocp-v4.0-art-dev@sha256:e045fad043f28570b754619999ffb356bedee81ff842c56a32b1b13588fc1651"
            }
          },
          "name": "kube-scheduler-recovery-controller"
        }
      ],
      "annotations": {
        "kubectl.kubernetes.io/default-container": "kube-scheduler",
        "kubernetes.io/config.hash": "70ff5515b34390af0ccffeea43283983",
        "kubernetes.io/config.mirror": "70ff5515b34390af0ccffeea43283983",
        "kubernetes.io/config.seen": "2023-01-18T19:48:25.118069839Z",
        "kubernetes.io/config.source": "file",
        "target.workload.openshift.io/management": "{\"effect\": \"PreferredDuringScheduling\"}"
      }
    },
    "violations": [
      {
        "message": "RHSA-2023:0594 (CVSS 9.8) (severity Important) found in component 'libksba' (version 1.3.5-8.el8_6.x86_64) in container 'kube-scheduler'"
      },
      {
        "message": "RHSA-2023:0594 (CVSS 9.8) (severity Important) found in component 'libksba' (version 1.3.5-8.el8_6.x86_64) in container 'kube-scheduler-cert-syncer'"
      },
      {
        "message": "RHSA-2023:0594 (CVSS 9.8) (severity Important) found in component 'libksba' (version 1.3.5-8.el8_6.x86_64) in container 'kube-scheduler-recovery-controller'"
      }
    ],
    "time": "2023-03-18T15:35:17.220589110Z",
    "firstOccurred": "2023-03-18T15:35:17.220589110Z"
  }
}